pysmme/__init__.py
pysmme/_smme.cpython-39-darwin.so
pysmme/tools.py
pysmme/transforms.py
pysmme-1.0.dist-info/LICENSE.note
pysmme-1.0.dist-info/METADATA
pysmme-1.0.dist-info/WHEEL
pysmme-1.0.dist-info/top_level.txt
pysmme-1.0.dist-info/RECORD
