Metadata-Version: 2.1
Name: pysmme
Version: 1.0
Summary: Soft maximin estimation in Python
Home-page: https://adam-lund.github.io
Author: Adam Lund
Author-email: adam.lund@math.ku.dk
License: mit
Platform: UNKNOWN
Classifier: Development Status :: 5 - Production/Stable
Classifier: Intended Audience :: Education
Classifier: Operating System :: MacOS
Classifier: License :: OSI Approved :: MIT License
Classifier: Programming Language :: Python :: 3
Requires-Python: >=3.6
License-File: LICENSE.note
